kiln_ai/__init__.py
kiln_ai/adapters/__init__.py
kiln_ai/adapters/adapter_registry.py
kiln_ai/adapters/docker_model_runner_tools.py
kiln_ai/adapters/ml_embedding_model_list.py
kiln_ai/adapters/ml_model_list.py
kiln_ai/adapters/ollama_tools.py
kiln_ai/adapters/prompt_builders.py
kiln_ai/adapters/provider_tools.py
kiln_ai/adapters/remote_config.py
kiln_ai/adapters/reranker_list.py
kiln_ai/adapters/run_output.py
kiln_ai/adapters/test_adapter_registry.py
kiln_ai/adapters/test_docker_model_runner_tools.py
kiln_ai/adapters/test_ml_embedding_model_list.py
kiln_ai/adapters/test_ml_model_list.py
kiln_ai/adapters/test_ollama_tools.py
kiln_ai/adapters/test_prompt_adaptors.py
kiln_ai/adapters/test_prompt_builders.py
kiln_ai/adapters/test_provider_tools.py
kiln_ai/adapters/test_remote_config.py
kiln_ai/adapters/test_reranker_list.py
kiln_ai/adapters/chat/__init__.py
kiln_ai/adapters/chat/chat_formatter.py
kiln_ai/adapters/chat/test_chat_formatter.py
kiln_ai/adapters/chunkers/__init__.py
kiln_ai/adapters/chunkers/base_chunker.py
kiln_ai/adapters/chunkers/chunker_registry.py
kiln_ai/adapters/chunkers/embedding_wrapper.py
kiln_ai/adapters/chunkers/fixed_window_chunker.py
kiln_ai/adapters/chunkers/helpers.py
kiln_ai/adapters/chunkers/semantic_chunker.py
kiln_ai/adapters/chunkers/test_base_chunker.py
kiln_ai/adapters/chunkers/test_chunker_registry.py
kiln_ai/adapters/chunkers/test_embedding_wrapper.py
kiln_ai/adapters/chunkers/test_fixed_window_chunker.py
kiln_ai/adapters/chunkers/test_helpers.py
kiln_ai/adapters/chunkers/test_semantic_chunker.py
kiln_ai/adapters/data_gen/__init__.py
kiln_ai/adapters/data_gen/data_gen_prompts.py
kiln_ai/adapters/data_gen/data_gen_task.py
kiln_ai/adapters/data_gen/qna_gen_task.py
kiln_ai/adapters/data_gen/test_data_gen_task.py
kiln_ai/adapters/data_gen/test_qna_gen_task.py
kiln_ai/adapters/embedding/__init__.py
kiln_ai/adapters/embedding/base_embedding_adapter.py
kiln_ai/adapters/embedding/embedding_registry.py
kiln_ai-0.23.0.dist-info/METADATA
kiln_ai-0.23.0.dist-info/WHEEL
kiln_ai-0.23.0.dist-info/licenses/LICENSE.txt
kiln_ai-0.23.0.dist-info/RECORD
