Metadata-Version: 2.4
Name: kiln-ai
Version: 0.23.0
Summary: Kiln AI
Project-URL: Homepage, https://kiln.tech
Project-URL: Repository, https://github.com/Kiln-AI/kiln
Project-URL: Documentation, https://kiln-ai.github.io/Kiln/kiln_core_docs/kiln_ai.html
Project-URL: Issues, https://github.com/Kiln-AI/kiln/issues
Author-email: "Steve Cosman, Chesterfield Laboratories Inc" <scosman@users.noreply.github.com>
License-File: LICENSE.txt
Classifier: Intended Audience :: Developers
Classifier: License :: OSI Approved :: MIT License
Classifier: Programming Language :: Python :: 3.10
Classifier: Programming Language :: Python :: 3.11
Classifier: Programming Language :: Python :: 3.12
Classifier: Programming Language :: Python :: 3.13
Requires-Python: >=3.10
Requires-Dist: anyio>=4.10.0
Requires-Dist: boto3>=1.37.10
Requires-Dist: coverage>=7.6.4
Requires-Dist: exceptiongroup>=1.0.0; python_version < '3.11'
Requires-Dist: google-cloud-aiplatform>=1.84.0
Requires-Dist: google-genai>=1.21.1
Requires-Dist: jsonschema>=4.23.0
Requires-Dist: lancedb>=0.24.2
Requires-Dist: litellm>=1.79.3
Requires-Dist: llama-index-vector-stores-lancedb>=0.4.2
Requires-Dist: llama-index>=0.13.3
Requires-Dist: openai>=1.53.0
Requires-Dist: pdoc>=15.0.0
Requires-Dist: pillow>=11.1.0
Requires-Dist: pydantic>=2.9.2
Requires-Dist: pypdf>=6.0.0
Requires-Dist: pypdfium2>=4.30.0
Requires-Dist: pytest-benchmark>=5.1.0
Requires-Dist: pytest-cov>=6.0.0
Requires-Dist: pyyaml>=6.0.2
Requires-Dist: together
Requires-Dist: typing-extensions>=4.12.2
Requires-Dist: vertexai>=1.43.0
